{"cameraMode":{"drawMode":0,"name":"Shaded","section":"Shading Mode"},"sceneLighting":true,"audioPlay":false,"sceneViewState":{"m_AlwaysRefresh":false,"showFog":true,"showSkybox":true,"showFlares":true,"showImageEffects":true,"showParticleSystems":true,"showVisualEffectGraphs":true,"m_FxEnabled":true},"in2DMode":false,"pivot":{"x":17.2926025390625,"y":-2.5325703620910646,"z":4.616348743438721},"rotation":{"x":0.1293620467185974,"y":0.4234060049057007,"z":-0.06019105389714241,"w":0.895179033279419},"size":14.030169486999512,"orthographic":false}